{
  "meta": {
    "lang": "he",
    "title": "DRMN — צלילי שינה, רעש לבן ומכונת צלילים ל-iPhone",
    "description": "אפליקציית צלילי שינה ל-iPhone: גשם, מאוורר, רעש לבן, מיקס ואופליין. הורידו את DRMN בחינם מ-App Store — צלילי שינה, ריכוז ושינה לתינוק.",
    "keywords": "צלילי שינה, מכונת צלילים לשינה, רעש לבן, צליל גשם לשינה, צליל מאוורר, אפליקציית שינה, רעש לבן אפליקציה, צלילי תינוק, ריכוז, שינה אופליין",
    "author": "DRMN",
    "og_url": "https://drmn.xyz/he/",
    "og_title": "מכונת צלילים לשינה וצלילי שינה | DRMN",
    "og_description": "מכונת צלילים לשינה ל-iPhone: גשם, מאוורר, רעש לבן וצלילי טבע. מיקס, אופליין. הורידו את DRMN בחינם מ-App Store.",
    "og_image": "https://drmn.xyz/he/site_preview.png",
    "og_image_alt": "אפליקציית DRMN — ישנים טוב יותר, נרדמים מהר יותר",
    "og_locale": "he_IL",
    "twitter_url": "https://drmn.xyz/he/",
    "twitter_title": "מכונת צלילים לשינה וצלילי שינה | DRMN",
    "twitter_description": "מכונת צלילים לשינה ל-iPhone: גשם, מאוורר, רעש לבן וצלילי טבע. מיקס, אופליין. הורידו את DRMN בחינם מ-App Store.",
    "twitter_image": "https://drmn.xyz/he/site_preview.png",
    "twitter_image_alt": "אפליקציית DRMN — ישנים טוב יותר, נרדמים מהר יותר",
    "twitter_site": "@c__basso",
    "twitter_creator": "@c__basso",
    "canonical": "https://drmn.xyz/he/",
    "app_store_id": "6746480683",
    "og_type": "website",
    "twitter_card": "summary_large_image",
    "theme_color": "#1a1b2e",
    "apple_mobile_web_app_status_bar_style": "default",
    "og_image_width": "1200",
    "og_image_height": "630",
    "twitter_image_width": "1200",
    "twitter_image_height": "630"
  },
  "header": {
    "app_name_suffix": "מכונת צלילים לשינה",
    "logo_alt": "לוגו אפליקציית DRMN צלילי שינה ל-iPhone",
    "app_name": "DRMN",
    "title": "אפליקציית מכונת צלילים לשינה ל-iPhone",
    "tagline": "נרדמים מהר יותר עם צלילי השינה הטובים ביותר. DRMN היא אפליקציית צלילי שינה עם גשם, מאוורר, רעש לבן וצלילי טבע — עם מיקס, אופליין וחיסכון בסוללה לכל הלילה.",
    "tldr": "DRMN היא אפליקציית צלילי שינה חינמית ל-iOS שעוזרת לנרדם 30–50% מהר יותר. גרסה חינמית: גשם, מאוורר, רעש לבן, טיימר של שעה, אופליין, מיקס ואופטימיזציה לסוללה. הורידו בחינם מ-App Store.",
    "download_text": "הורידו עכשיו",
    "download_url": "https://apps.apple.com/app/id6746480683",
    "download_aria_label": "הורידו אפליקציית צלילי שינה בחינם מ-App Store",
    "download_img_alt": "הורידו אפליקציית צלילי שינה ב-App Store",
    "scan_to_download": "סרקו להורדה"
  },
  "stats": {
    "title": "DRMN במספרים",
    "items": [
      {
        "stat": "4.9/5",
        "description": "דירוג ממוצע ב-App Store (10 ביקורות)"
      },
      {
        "stat": "10,000+",
        "description": "משתמשים שהורידו את DRMN מ-App Store"
      },
      {
        "stat": "30–50% מהר יותר",
        "description": "שיפור ממוצע בזמן ההירדמות"
      },
      {
        "stat": "100 שעות",
        "description": "צלילי שינה ואודיו אמביינט מוקלטים באופן מקצועי"
      },
      {
        "stat": "10 שעות",
        "description": "השמעה אופליין בטעינה אחת (סוללה מותאמת)"
      },
      {
        "stat": "49.2 MB",
        "description": "גודל האפליקציה (מותאם לכל דגמי iPhone)"
      },
      {
        "stat": "iOS 17.1+",
        "description": "תואם לכל דגמי iPhone המודרניים"
      }
    ]
  },
  "features": {
    "title": "צלילי שינה וטבע למנוחה טובה יותר",
    "items": [
      {
        "icon": "🌊",
        "title": "ספרייה עשירה של צלילי שינה",
        "description": "בחרו מרעש לבן, רעש חום ורעש כהה להרפיה עמוקה. גלו צלילי טבע: גשם עדין, גלים, אש וציפורי בוקר. גם מסלולי מדיטציה אמביינטיים וכלי נגינה רכים. ערבבו צלילים לסביבת שינה מושלמת."
      },
      {
        "icon": "😴",
        "title": "נרדמים מהר יותר, ישנים עמוק יותר",
        "description": "קשה להירדם? טיפול קולי מבוסס מדע מסתיר רעשי תנועה, שכנים ונחירות. סביבת שינה עקבית שמסמנת למוח שעת מנוחה. קומו רעננים כל בוקר."
      },
      {
        "icon": "🎯",
        "title": "ריכוז טוב יותר, עבודה חכמה יותר",
        "description": "מדיטציה, לימודים או עבודה בבית קפה רועש — DRMN יוצרת את האווירה המושלמת לריכוז. חסמו הסחות דעת, הפחיתו לחץ והגבירו פרодуктיביות."
      },
      {
        "icon": "👶",
        "title": "עזרו לתינוק לישון בשקט",
        "description": "צלילי שינה מיוחדים לתינוקות — מייבש שיער, שואב אבק והקלדה — עוזרים לתינוקות ופעוטות להירדם מהר יותר. קצבים מוכרים מרגיעים ומקדמים שינה בריאה."
      }
    ]
  },
  "popular_sounds": {
    "title": "צלילי שינה פופולריים",
    "intro": "מחפשים את הצליל הטוב ביותר לשינה? ב-DRMN הצלילים המבוקשים ביותר — מוכנים למיקס, אופליין ולילה שלם ב-iPhone.",
    "items": [
      {
        "icon": "🌧️",
        "title": "צליל גשם לשינה",
        "description": "גשם עדין מסתיר רעשים פתאומיים ועוזר להירדם. ערבבו גשם עם רעש לבן לשינה עמוקה יותר."
      },
      {
        "icon": "🌀",
        "title": "צליל מאוורר לשינה",
        "description": "המממם קבוע של מאוורר חוסם תנועה, נחירות ושכנים — קלאסיקת צלילי השינה."
      },
      {
        "icon": "🔊",
        "title": "רעש לבן לשינה",
        "description": "רעש לבן, חום וכהה יוצרים שכבת רקע עקבית שמסמנת למוח לנוח."
      },
      {
        "icon": "🌊",
        "title": "צלילי טבע לשינה",
        "description": "גלים, אש וציפורי בוקר משלימים את הספרייה — ערבבו עם גשם או מאוורר בכל עת."
      }
    ]
  },
  "content": {
    "title": "שפרו את השינה עם אפליקציית מכונת צלילים",
    "intro": "DRMN היא אפליקציית צלילי שינה ל-iOS עם רעש לבן, גשם, מאוורר וצלילי טבע להירדמות מהירה יותר. מעל 10,000 הורדות ודירוג 4.9. מושלמת לנדוד שינה, ריכוז ושינת תינוק.",
    "sections": [
      {
        "title": "ספריית צלילים לפי הצרכים שלכם",
        "paragraph1": "אספנו צלילים איכותיים להרפיה, ריכוז ושינה טובה יותר:",
        "list_items": [
          "<strong>רעש לבן, חום וכהה</strong> — מסתיר רעשים מפריעים ויוצר סביבת שינה עקבית",
          "<strong>צלילי טבע</strong> — גשם, גלים, אש, מאוורר וציפורי בוקר מעבירים למקום שקט",
          "<strong>מדיטציה וריכוז</strong> — מסלולים אמביינטיים וכלי נגינה רכים לעבודה ומיינדפולנס",
          "<strong>צלילי שינה לתינוק</strong> — מייבש שיער, שואב אבק והקלדה עוזרים לקטנטנים להירדם"
        ],
        "paragraph2": "הכי טוב? אפשר לערבב כמה צלילים. רעש לבן עם גלים או גשם עם מוזיקת מדיטציה — בשליטה מלאה."
      },
      {
        "title": "טיפול שינה מבוסס מדע שעובד",
        "paragraph1": "מחקרים מראים: רקע קולי עקבי משפר משמעותית את איכות השינה. איך DRMN עוזרת:",
        "list_items": [
          "<strong>חוסם רעשים מפריעים</strong> — תנועה, שכנים, נחירות לא יעירו יותר",
          "<strong>מסמן למוח לנוח</strong> — צליל עקבי עוזר להירגע",
          "<strong>מקדם שינה עמוקה</strong> — תדרים נבחרים תומכים במחזורי שינה משקמים"
        ],
        "paragraph2": "מעל 10,000 הורדות ו-4.9 ב-App Store. משתמשים נרדמים 30–50% מהר יותר בממוצע ומתעוררים פחות בלילה. התחילו את היום באנרגיה."
      },
      {
        "title": "לא רק לשינה — גם לריכוז",
        "paragraph1": "DRMN היא לא רק אפליקציית שינה — כלי סודי לריכוז. בית קפה רועש, מבחן או מדיטציה — הצלילים הנכונים משנים הכל:",
        "list_items": [
          "<strong>מסיר הסחות דעת</strong> — בועת שקט בכל מקום",
          "<strong>מפחית לחץ</strong> — תדרים מרגיעים לשמירה על ריכוז",
          "<strong>מגביר פרודוקטיביות</strong> — רבים מתרכזים טוב יותר עם רקע קולי",
          "<strong>מעמיק ריכוז</strong> — מושלם לעבודה ממוקדת ומשימות חשובות"
        ],
        "paragraph2": "עבודה מהבית, לימודים בלילה או רגע של שלווה — DRMN מספקת את הרקע הקולי המושלם."
      },
      {
        "title": "עזרו לקטנטן לישון כל הלילה",
        "paragraph1": "יודעים כמה מתיש כשהתינוק לא רוצה לישון. לכן הוספנו צלילים מיוחדים לתינוקות ופעוטות. מייבש שיער עדין, שואב אבק והקלדה יוצרים קצבים מוכרים.",
        "list_items": [],
        "paragraph2": "צלילים עדינים ועקביים מזכירים רעשים ברחם ונותנים תחושת ביטחון. הורים ברחבי העולם סומכים על DRMN — וגם אתם תישנו טוב יותר."
      },
      {
        "title": "נבנה לחיים האמיתיים",
        "paragraph1": "כל פרט תוכנן כדי ש-DRMN תתאים ליום-יום:",
        "list_items": [
          "<strong>הקלטה מקצועית</strong> — מעל 100 שעות אודיו איכותי",
          "<strong>מיקס ושילובים</strong> — צרו את התערובת המושלמת",
          "<strong>טיימר שינה חכם</strong> — דעיכה אוטומטית, בלי דאגה לכל הלילה",
          "<strong>ממשק פשוט ויפה</strong> — מוכן תוך שניות",
          "<strong>עובד אופליין</strong> — הורידו מועדפים ותיהנו עד 10 שעות בלי אינטרנט",
          "<strong>חיסכון בסוללה</strong> — כל הלילה בלי לרוקן את iPhone",
          "<strong>התחלה חינמית</strong> — נסו בחינם, פרימיום אופציונלי"
        ],
        "paragraph2": "DRMN עובדת ב-iPhone עם iOS 17.1+. גרסה חינמית: טיימר שעה, אופליין, מיקס ואופטימיזציה לסוללה. פרימיום פותח השמעה ארוכה יותר ועוד צלילים."
      }
    ]
  },
  "benefits": {
    "title": "למה DRMN?",
    "items": [
      "צלילים מקצועיים שבאמת עוזרים להירדם",
      "ערבבו כמה צלילים לסביבת שינה מושלמת",
      "טיימר חכם עם דעיכה אוטומטית — הגדירו ושכחו",
      "ממשק יפה ונוח, קל לשימוש",
      "עובד אופליין לגמרי אחרי הורדת צלילים",
      "סוללה מותאמת לכל הלילה",
      "הורדה חינמית, פרימיום אופציונלי"
    ]
  },
  "comparison": {
    "title": "מכונת הצלילים הטובה ביותר — השוואת DRMN",
    "description": "איך DRMN מושווית לאפליקציות חינמיות ואפליקציות בתשלום טיפוסיות. מבוסס על נתונים ציבוריים ומשוב משתמשים.",
    "table": {
      "headers": [
        "תכונה",
        "DRMN",
        "אפליקציות חינמיות טיפוסיות",
        "אפליקציות בתשלום"
      ],
      "rows": [
        {
          "feature": "גרסה חינמית",
          "drmn": "טיימר שעה (מספיק לשינה)",
          "typical": "צלילים מוגבלים או פרסומות",
          "premium": "נדרש מנוי"
        },
        {
          "feature": "אופליין",
          "drmn": "כן (10+ שעות)",
          "typical": "מוגבל או עם פרסומות",
          "premium": "כן"
        },
        {
          "feature": "מיקס צלילים",
          "drmn": "כן, ללא הגבלה",
          "typical": "לא או מוגבל",
          "premium": "כן"
        },
        {
          "feature": "אופטימיזציה לסוללה",
          "drmn": "כן, כל הלילה",
          "typical": "חלקי",
          "premium": "כן"
        },
        {
          "feature": "צלילי תינוק",
          "drmn": "כן (מייבש שיער, שואב, מקלדת)",
          "typical": "לא",
          "premium": "לפעמים"
        },
        {
          "feature": "טיימר שינה",
          "drmn": "דעיכה אוטומטית",
          "typical": "בסיסי",
          "premium": "דעיכה אוטומטית"
        },
        {
          "feature": "גודל קובץ",
          "drmn": "49.2 MB",
          "typical": "30–70 MB",
          "premium": "50–100 MB"
        },
        {
          "feature": "דרישת iOS",
          "drmn": "17.1+",
          "typical": "15.0+",
          "premium": "16.0+"
        },
        {
          "feature": "דירוג App Store",
          "drmn": "4.9/5 (10 ביקורות)",
          "typical": "3.5–4.5/5",
          "premium": "4.0–4.8/5"
        }
      ]
    }
  },
  "testimonials": {
    "title": "מה משתמשים אומרים על DRMN",
    "items": [
      {
        "quote": "נרדמת 40% מהר יותר עם DRMN. המיקס מאפשר לשלב רעש לבן וגלים. השינה הטובה ביותר בשנים!",
        "name": "Sarah M.",
        "location": "קליפורניה, ארה\"ב",
        "role": "איש מקצוע"
      },
      {
        "quote": "התינוק שלנו ישן כל הלילה בזכות צליל מייבש השיער. הדבר היחיד שעובד בעקביות. אופליין מציל בנסיעות.",
        "name": "Michael R.",
        "location": "טקסס, ארה\"ב",
        "role": "הורה"
      },
      {
        "quote": "עם נדודי שינה DRMN שינתה הכל. משתמשת כל לילה וקמה רעננה. לא דואגת יותר לסוללה.",
        "name": "Jennifer L.",
        "location": "ניו יורק, ארה\"ב",
        "role": "נדודי שינה"
      },
      {
        "quote": "משתמש ב-DRMN לריכוז בעבודה. המיקס יוצר סביבה מושלמת. טיימר שעה חינמי — ערך מדהים!",
        "name": "David K.",
        "location": "לונדון, בריטניה",
        "role": "עובד מהבית"
      }
    ]
  },
  "whats_new": {
    "title": "מה חדש",
    "description": "עדכונים אחרונים ב-DRMN",
    "items": [
      {
        "date": "ינואר 2025",
        "title": "אופטימיזציה משופרת לסוללה",
        "description": "יעילות גבוהה יותר לכל הלילה. עד 10 שעות השמעה רציפה בטעינה אחת."
      },
      {
        "date": "ינואר 2025",
        "title": "צלילי שינה חדשים",
        "description": "10 הקלטות מקצועיות חדשות — ספרייה של מעל 100 שעות."
      },
      {
        "date": "דצמבר 2024",
        "title": "מיקס צלילים משופר",
        "description": "איכות אודיו טובה יותר ומעברים חלקים יותר בין צלילים."
      }
    ]
  },
  "final_cta": {
    "title": "מוכנים לישון טוב יותר הלילה?",
    "paragraph1": "הצטרפו ליותר מ-10,000 משתמשים ששיפרו את השינה עם DRMN. 4.9/5 ב-App Store — אפליקציית צלילי שינה חינמית שעוזרת לנרדם 30–50% מהר יותר. גרסה חינמית: טיימר שעה, אופליין ומיקס. הורידו היום ונסו צלילים מקצועיים בחינם.",
    "cta_text": "הורידו אפליקציית צלילי שינה בחינם",
    "cta_url": "https://apps.apple.com/app/id6746480683",
    "cta_aria_label": "הורידו אפליקציית צלילי שינה בחינם מ-App Store",
    "cta_img_alt": "הורידו אפליקציית צלילי שינה ב-App Store"
  },
  "footer": {
    "copyright": "© 2025 DRMN. כל הזכויות שמורות.",
    "privacy_link": "מדיניות פרטיות",
    "privacy_url": "/privacy.html",
    "terms_link": "תנאי שימוש",
    "terms_url": "/terms.html",
    "blog_link": "בלוג",
    "fazier_badge_alt": "תג Fazier",
    "superlaunch_badge_alt": "מומלץ ב-Super Launch"
  },
  "app_info": {
    "developer": "Vladimir Ivakhnenko",
    "category": "בריאות וכושר",
    "age_rating": "4+",
    "file_size": "49.2 MB",
    "compatibility": "נדרש iOS 17.1 ומעלה",
    "platform": "iPhone",
    "copyright": "© 2025 c-basso",
    "in_app_purchases": true,
    "subscriptions": [
      {
        "name": "White Noise Machine",
        "description": "שינה טובה יותר עם צלילי שינה ב-DRMN",
        "price": "$5.99",
        "type": "ניסיון חינם"
      },
      {
        "name": "Lifetime Plan",
        "description": "רכישה חד-פעמית לגישה לכל החיים",
        "price": "$19.99",
        "type": "חד-פעמי"
      }
    ]
  },
  "seo": {
    "breadcrumb_home": "בית",
    "faq_title": "שאלות נפוצות: מכונת צלילים, צלילי שינה ורעש לבן",
    "faq": [
      {
        "question": "מה הצליל הטוב ביותר לשינה?",
        "answer": "תלוי בכם — רבים בוחרים גשם, מאוורר או רעש לבן קבוע. ב-DRMN אפשר להאזין ולערבב צלילים ולמצוא מה עוזר להירדם הכי מהר."
      },
      {
        "question": "מה זו מכונת צלילים לשינה?",
        "answer": "מנגנת רקע קבוע — גשם, מאוורר או רעש לבן — כדי לכסות רעש ולעזור לישון. DRMN היא אפליקציה ל-iPhone עם מיקס, אופליין וטיימר שינה, כמו מכונה פיזית."
      },
      {
        "question": "אפליקציית רעש לבן הטובה ביותר ל-iPhone?",
        "answer": "ל-DRMN דירוג 4.9 ומעל 10,000 הורדות. גשם, מאוורר, רעש לבן ו-100 שעות צלילי שינה וטבע — משתמשים נרדמים 30–50% מהר יותר."
      },
      {
        "question": "יש אפליקציית רעש לבן חינמית?",
        "answer": "כן! DRMN חינמית ב-App Store. הגרסה החינמית כוללת טיימר שעה, אופליין, מיקס וגישה לצלילי שינה. פרימיום פותח השמעה ארוכה יותר."
      },
      {
        "question": "אילו צלילים יש באפליקציית השינה?",
        "answer": "DRMN מציעה מעל 100 שעות אודיו מקצועי: רעש לבן, חום וכהה, גשם, גלים, אש, ציפורי בוקר, מדיטציה וצלילי תינוק (מייבש, שואב, מקלדת)."
      },
      {
        "question": "האפליקציה עובדת אופליין?",
        "answer": "כן! אחרי הורדת צלילים DRMN עובדת אופליין לגמרי. עם אופטימיזציה לסוללה — עד 10 שעות בלי אינטרנט."
      },
      {
        "question": "אפליקציה הטובה ביותר לשינת תינוק?",
        "answer": "DRMN כוללת צלילי תינוק מיוחדים (מייבש, שואב, מקלדת) שעוזרים להירדם מהר יותר. קצבים מוכרים מרגיעים ויוצרים סביבה שקטה."
      },
      {
        "question": "איך עובדת אפליקציית מכונת צלילים?",
        "answer": "DRMN מספקת רעש לבן וצלילי שינה למנוחה וריכוז. מכסה רעש, יוצרת סביבה עקבית ומקדמת שינה עמוקה — כמו מכונה פיזית."
      },
      {
        "question": "אפשר לערבב צלילים?",
        "answer": "כן! שלבו רעש לבן עם גלים או גשם עם מדיטציה. צרו חוויית שינה משלכם."
      },
      {
        "question": "יש טיימר שינה?",
        "answer": "כן! טיימר עם דעיכה אוטומטית. הגדירו — הצליל ידעך לאט אחרי שנרדמתם."
      },
      {
        "question": "מה זה רעש לבן לשינה ואיך הוא עוזר?",
        "answer": "צליל קבוע שמכסה רעשים מפריעים ועוזר להירדם מהר יותר. DRMN חוסמת תנועה, שכנים ורעשים אחרים לסביבת שינה עקבית."
      },
      {
        "question": "מתאים לנדוד שינה?",
        "answer": "כן! ל-DRMN 4.9 ומעל 10,000 הורדות. בכיסוי רעש משתמשים נרדמים 30–50% מהר יותר בממוצע. הורידו בחינם."
      },
      {
        "question": "כמה הורדות יש ל-DRMN?",
        "answer": "מעל 10,000 ב-App Store, 4.9/5 מ-10 ביקורות. 100 שעות צלילים ועד 10 שעות אופליין בטעינה אחת."
      },
      {
        "question": "מה דירוג DRMN ב-App Store?",
        "answer": "4.9/5 מ-10 ביקורות. מעל 10,000 הורדות, 100 שעות צלילי שינה והשמעה אופליין."
      },
      {
        "question": "במה DRMN שונה מאפליקציות אחרות?",
        "answer": "DRMN בולטת בגרסה חינמית נדיבה (טיימר שעה), מיקס מתקדם, צלילי תינוק ואופטימיזציה לסוללה — אופליין וצלילים מקצועיים בלי מנוי."
      },
      {
        "question": "מה ייחודי ב-DRMN לעומת חלופות חינמיות?",
        "answer": "גרסה חינמית עם טיימר שעה בלי מנוי. בעוד אחרות מגבילות צלילים או דורשות רכישות, DRMN נותנת מיקס, אופליין וסוללה בחינם — ובנוסף צלילי תינוק שחסרים אצל רבים."
      },
      {
        "question": "האם DRMN טובה יותר מאפליקציות צלילי שינה אחרות?",
        "answer": "גרסה חינמית: טיימר, מיקס, אופליין, סוללה בלי מנוי. 4.9, מעל 10,000 הורדות, הירדמות 30–50% מהר יותר. צלילי תינוק וטיימר חכם בחינם — תכונות שאחרות גובות עליהן."
      }
    ],
    "structured_data": {
      "software_application": {
        "@context": "https://schema.org",
        "@type": "MobileApplication",
        "name": "DRMN",
        "alternateName": "אפליקציית השינה DRMN",
        "applicationCategory": "HealthApplication",
        "operatingSystem": "iOS",
        "offers": {
          "@type": "Offer",
          "price": "0",
          "priceCurrency": "USD",
          "availability": "https://schema.org/InStock",
          "url": "https://apps.apple.com/app/id6746480683"
        },
        "description": "אפליקציית צלילי שינה ורעש לבן ל-iPhone. גרסה חינמית עם גשם, מאוורר, מיקס ואופליין. לשינה, ריכוז ותינוקות.",
        "image": {
          "@type": "ImageObject",
          "url": "https://drmn.xyz/img/logo.webp",
          "width": 176,
          "height": 176,
          "caption": "לוגו אפליקציית DRMN"
        },
        "screenshot": {
          "@type": "ImageObject",
          "url": "https://drmn.xyz/img/logo.webp",
          "width": 176,
          "height": 176
        },
        "url": "https://drmn.xyz/he/",
        "author": {
          "@type": "Person",
          "name": "Vladimir Ivakhnenko"
        },
        "publisher": {
          "@type": "Person",
          "name": "Vladimir Ivakhnenko"
        },
        "keywords": "צלילי שינה, מכונת צלילים, רעש לבן, אפליקציית שינה, צליל גשם, צליל מאוורר, שינה אופליין",
        "inLanguage": "he",
        "datePublished": "2024-01-01",
        "dateModified": "2025-01-15",
        "softwareVersion": "1.5",
        "fileSize": "49.2MB",
        "softwareRequirements": "נדרש iOS 17.1 ומעלה",
        "aggregateRating": {
          "@type": "AggregateRating",
          "ratingValue": "4.9",
          "ratingCount": "10"
        }
      },
      "organization": {
        "@context": "https://schema.org",
        "@type": "Organization",
        "name": "DRMN",
        "url": "https://drmn.xyz/he/",
        "logo": "https://drmn.xyz/img/logo.webp",
        "description": "DRMN — אפליקציית צלילי שינה ורעש לבן ל-iPhone. גרסה חינמית עם מיקס ואופליין. לשינה, ריכוז ותינוקות."
      },
      "website": {
        "@context": "https://schema.org",
        "@type": "WebSite",
        "name": "DRMN",
        "url": "https://drmn.xyz/he/",
        "description": "אפליקציית צלילי שינה ורעש לבן ל-iPhone. גרסה חינמית עם מיקס ואופליין. הורידו בחינם מ-App Store.",
        "potentialAction": {
          "@type": "SearchAction",
          "target": "https://drmn.xyz/?q={search_term_string}",
          "query-input": "required name=search_term_string"
        }
      },
      "howto": {
        "@context": "https://schema.org",
        "@type": "HowTo",
        "name": "איך להשתמש באפליקציית צלילי שינה",
        "description": "למדו איך להשתמש ב-DRMN להירדמות מהירה יותר. מדריך שלב-אחר-שלב.",
        "step": [
          {
            "@type": "HowToStep",
            "position": 1,
            "name": "הורידו בחינם",
            "text": "הורידו את DRMN מ-App Store ל-iPhone. נדרש iOS 17.1+. הגרסה החינמית כוללת טיימר שעה.",
            "url": "https://apps.apple.com/app/id6746480683"
          },
          {
            "@type": "HowToStep",
            "position": 2,
            "name": "עיינו בצלילי שינה",
            "text": "פתחו את האפליקציה וגלו בספרייה: רעש לבן וחום, טבע (גשם, גלים, אש), מדיטציה וצלילי תינוק."
          },
          {
            "@type": "HowToStep",
            "position": 3,
            "name": "בחרו צלילים",
            "text": "לפי הצורך — רעש לבן לכיסוי, טבע להרפיה, צלילי תינוק לקטנטנים. האזינו לפני השמעה."
          },
          {
            "@type": "HowToStep",
            "position": 4,
            "name": "ערבבו צלילים",
            "text": "שלבו רעש לבן עם גלים או גשם עם מדיטציה. צרו סביבת שינה מושלמת."
          },
          {
            "@type": "HowToStep",
            "position": 5,
            "name": "הגדירו טיימר שינה",
            "text": "הפעילו דעיכה אוטומטית אם לא רוצים צליל כל הלילה. העוצמה תדעך לאט."
          },
          {
            "@type": "HowToStep",
            "position": 6,
            "name": "הפעילו וישנו",
            "text": "לחצו play וכוונו עוצמה. iPhone ליד או אוזניות — שניהם עובדים."
          },
          {
            "@type": "HowToStep",
            "position": 7,
            "name": "הורידו לאופליין",
            "text": "הורידו מועדפים לשימוש בלי אינטרנט. שינה רציפה בכל מקום."
          }
        ]
      }
    }
  }
}
